stactools/noaa_hrrr/__init__.py
stactools/noaa_hrrr/commands.py
stactools/noaa_hrrr/constants.py
stactools/noaa_hrrr/inventory.py
stactools/noaa_hrrr/metadata.py
stactools/noaa_hrrr/stac.py
stactools/noaa_hrrr/data/inventory__alaska__nat.csv.gz
stactools/noaa_hrrr/data/inventory__alaska__prs.csv.gz
stactools/noaa_hrrr/data/inventory__alaska__sfc.csv.gz
stactools/noaa_hrrr/data/inventory__alaska__subh.csv.gz
stactools/noaa_hrrr/data/inventory__conus__nat.csv.gz
stactools/noaa_hrrr/data/inventory__conus__prs.csv.gz
stactools/noaa_hrrr/data/inventory__conus__sfc.csv.gz
stactools/noaa_hrrr/data/inventory__conus__subh.csv.gz
stactools/noaa_hrrr/data/variable_descriptions.csv.gz
stactools_noaa_hrrr-0.1.2.dist-info/LICENSE
stactools_noaa_hrrr-0.1.2.dist-info/METADATA
stactools_noaa_hrrr-0.1.2.dist-info/WHEEL
stactools_noaa_hrrr-0.1.2.dist-info/top_level.txt
stactools_noaa_hrrr-0.1.2.dist-info/RECORD
