Metadata-Version: 2.1
Name: stactools-noaa-hrrr
Version: 0.1.2
Summary: NOAA High-Resolution Rapid Refresh (HRRR) stactools package
Author-email: Henry Rodman <henry@developmentseed.org>
Maintainer-email: Henry Rodman <henry@developmentseed.org>
License: Apache-2.0
Project-URL: Github, https://github.com/stactools-packages/noaa-hrrr
Project-URL: Issues, https://github.com/stactools-packages/noaa-hrrr/issues
Keywords: stactools,pystac,catalog,STAC
Classifier: Development Status :: 3 - Alpha
Classifier: Intended Audience :: Developers
Classifier: License :: OSI Approved :: Apache Software License
Classifier: Natural Language :: English
Classifier: Programming Language :: Python :: 3
Classifier: Programming Language :: Python :: 3.8
Classifier: Programming Language :: Python :: 3.9
Classifier: Programming Language :: Python :: 3.10
Classifier: Programming Language :: Python :: 3.11
Requires-Python: >=3.8
License-File: LICENSE
Requires-Dist: httpx~=0.27.0
Requires-Dist: pandas~=2.2.2
Requires-Dist: parse~=1.20.2
Requires-Dist: pystac~=1.10.1
Requires-Dist: rasterio~=1.3.10
Requires-Dist: stactools>=0.4.0
Provides-Extra: dev
Requires-Dist: black~=23.9; extra == "dev"
Requires-Dist: codespell~=2.2; extra == "dev"
Requires-Dist: jupyterlab~=4.2.1; extra == "dev"
Requires-Dist: mypy~=1.5; extra == "dev"
Requires-Dist: pre-commit~=3.4; extra == "dev"
Requires-Dist: pytest-cov~=4.1; extra == "dev"
Requires-Dist: pytest~=7.4; extra == "dev"
Requires-Dist: ruff==0.6.0; extra == "dev"
Provides-Extra: docs
Requires-Dist: pystac~=1.8; extra == "docs"
Requires-Dist: ipykernel~=6.25; extra == "docs"
Requires-Dist: jinja2~=3.1; extra == "docs"
